{
	"configurations" : 
	[
		{
			"directories" : 
			[
				{
					"build" : ".",
					"jsonFile" : "directory-.-Debug-d0094a50bb2071803777.json",
					"minimumCMakeVersion" : 
					{
						"string" : "3.1"
					},
					"projectIndex" : 0,
					"source" : ".",
					"targetIndexes" : 
					[
						0,
						1,
						2,
						3,
						4,
						5
					]
				}
			],
			"name" : "Debug",
			"projects" : 
			[
				{
					"directoryIndexes" : 
					[
						0
					],
					"name" : "Target",
					"targetIndexes" : 
					[
						0,
						1,
						2,
						3,
						4,
						5
					]
				}
			],
			"targets" : 
			[
				{
					"directoryIndex" : 0,
					"id" : "Target.bin::@6890427a1f51a3e7e1df",
					"jsonFile" : "target-Target.bin-Debug-da7fc1aa3f880071b130.json",
					"name" : "Target.bin",
					"projectIndex" : 0
				},
				{
					"directoryIndex" : 0,
					"id" : "Target.elf::@6890427a1f51a3e7e1df",
					"jsonFile" : "target-Target.elf-Debug-7e2c6fa14941967a7024.json",
					"name" : "Target.elf",
					"projectIndex" : 0
				},
				{
					"directoryIndex" : 0,
					"id" : "Target.hex::@6890427a1f51a3e7e1df",
					"jsonFile" : "target-Target.hex-Debug-17aa4735cb1b34fa93f6.json",
					"name" : "Target.hex",
					"projectIndex" : 0
				},
				{
					"directoryIndex" : 0,
					"id" : "clean-all::@6890427a1f51a3e7e1df",
					"jsonFile" : "target-clean-all-Debug-582d1fc38f3b8eba7a15.json",
					"name" : "clean-all",
					"projectIndex" : 0
				},
				{
					"directoryIndex" : 0,
					"id" : "flash::@6890427a1f51a3e7e1df",
					"jsonFile" : "target-flash-Debug-d7ef473fb8fdb160085c.json",
					"name" : "flash",
					"projectIndex" : 0
				},
				{
					"directoryIndex" : 0,
					"id" : "size::@6890427a1f51a3e7e1df",
					"jsonFile" : "target-size-Debug-45d6c802386bc352e82c.json",
					"name" : "size",
					"projectIndex" : 0
				}
			]
		}
	],
	"kind" : "codemodel",
	"paths" : 
	{
		"build" : "C:/Users/Laslo/Development/cpp/hbrs-praktikum/OpenRoboticBoard/UserApp/_Project/DemoX/build",
		"source" : "C:/Users/Laslo/Development/cpp/hbrs-praktikum/OpenRoboticBoard/UserApp/_Project/DemoX"
	},
	"version" : 
	{
		"major" : 2,
		"minor" : 5
	}
}
